Metadata-Version: 2.1
Name: MIDI2OSMapper
Version: 0.1b0
Summary: MIDI to OSC bridge
Home-page: 
Author: Linhdoha
Author-email: linhdoha@gmail.com
License: MIT
Platform: UNKNOWN
License-File: LICENSE
